{"publisher": "arale", "name": "popup", "family": "arale", "author": "\u504f\u53f3 <afc163@gmail.com>", "created_at": "2013-12-03T13:50:05Z", "distfiles": ["popup-debug.js", "popup.js"], "updated_at": "2014-05-09T05:39:45Z", "filename": "popup-1.1.6.tar.gz", "repository": {"url": "https://github.com/aralejs/popup.git", "type": "git"}, "keywords": ["widget"], "maintainers": ["\u504f\u53f3 <afc163@gmail.com>", "\u8d2f\u9ad8 <sakura9515@gmail.com>"], "version": "1.1.6", "bugs": {"url": "https://github.com/aralejs/popup/issues"}, "spm": {"output": ["popup.js"], "alias": {"$": "$", "overlay": "arale/overlay/1.1.4/overlay"}}, "dependencies": ["arale/overlay@1.1.4"], "readme": "# Popup\n\n---\n\n[![Build Status](https://travis-ci.org/aralejs/popup.png)](https://travis-ci.org/aralejs/popup)\n[![Coverage Status](https://coveralls.io/repos/aralejs/popup/badge.png?branch=master)](https://coveralls.io/r/aralejs/popup)\n\nPopup \u662f\u53ef\u89e6\u53d1\u7684\u6d6e\u5c42\u7ec4\u4ef6\u3002\u5c01\u88c5\u4e86\u5f53\u7528\u6237\u70b9\u51fb\u3001hover\u3001focus \u5230\u6307\u5b9a\u5143\u7d20\u65f6\uff0c\u53ef\u4ee5\u89e6\u53d1\u53e6\u4e00\u4e2a\u6d6e\u5c42\u663e\u793a\u7684\u884c\u4e3a\u3002\n\n---\n\nPopup \u7ee7\u627f\u81ea [overlay](http://aralejs.org/overlay/)\uff0c\u53ef\u4f7f\u7528\u5176\u4e2d\u5305\u62ec [widget](http://aralejs.org/widget/)\u3001[base](http://aralejs.org/base/)\u3001[class](http://aralejs.org/class/)\u3001[events](http://aralejs.org/events/)\u3001[attribute](http://aralejs.org/base/docs/attribute.html)\u3001[aspect](http://aralejs.org/base/docs/aspect.html) \u7684\u5c5e\u6027\u548c\u65b9\u6cd5\u3002\n\n\n## \u914d\u7f6e\u8bf4\u660e\n\n### element `element|string`\n\n\u5f39\u51fa\u7684\u6d6e\u5c42\u5143\u7d20\u3002\u4e5f\u53ef\u4ee5\u4f7f\u7528 template \u53c2\u6570\u4f20\u9012\u6a21\u677f\u6765\u4ee3\u66ff\u8fd9\u4e2a\u53c2\u6570\u3002\n\n### trigger `element|string`\n\n\u89e6\u53d1\u5143\u7d20\u3002\n\n### triggerType `string`\n\n\u89e6\u53d1\u7c7b\u578b\uff0c\u53ef\u9009[hover|click|focus]\uff0c\u9ed8\u8ba4\u4e3a hover\u3002\n\n### delegateNode `element|string` `1.0.2+`\n\n\u89e6\u53d1\u4e8b\u4ef6\u59d4\u6258\u7684\u5bf9\u8c61\u3002**\u5f53\u4f7f\u7528\u8fd9\u4e2a\u914d\u7f6e\u65f6\uff0c\u9700\u8981\u4fdd\u8bc1 trigger \u53c2\u6570\u662f\u4e00\u4e2a selector !!!**\n\n### effect `string`\n\n\u57fa\u7840\u7684\u52a8\u753b\u6548\u679c\uff0c\u53ef\u9009[fade|slide]\uff0c\u9ed8\u8ba4\u4e3a\u7a7a \u3002fade \u548c slide \u53ef\u4ee5\u5e76\u884c\u3002\n\n### duration `number`\n\n\u52a8\u753b\u65f6\u957f\uff0c\u9ed8\u8ba4 250 \u6beb\u79d2\u3002\n\n### delay `number`\n\n\u5ef6\u8fdf hover \u89e6\u53d1\u663e\u793a\u7684\u65f6\u957f\uff0c\u9ed8\u8ba4 70 \u6beb\u79d2\u3002\u8bbe\u4e3a`-1`\u65f6\uff0c\u8868\u793a popup \u6ca1\u6709\u5ef6\u8fdf\u663e\u793a\u548c\u9690\u85cf\u56e0\u7d20\u800c\u53d8\u4e3a tooltip \u7684\u6548\u679c\u3002\n\n### disabled `boolean`\n\n\u662f\u5426\u80fd\u89e6\u53d1\u5f39\u51fa\u6548\u679c\uff0c\u53ef\u7528`.set('disabled', true)`\u8fdb\u884c\u5f00\u5173\u3002\n\n\n> \u82e5\u6709\u8303\u4f8b\u548c\u6f14\u793a\u4e2d\u6709\u5176\u4ed6\u53c2\u6570\uff08\u5982\u81ea\u5b9a\u4e49\u4f4d\u7f6e\u53c2\u6570 align\uff09\uff0c\u8bf7\u53c2\u89c1 Popup \u7684\u7236\u7c7b [Overlay](http://aralejs.org/overlay/)\u3002\n\n## \u5c5e\u6027\n\n### activeTrigger\n\n\u603b\u662f\u6307\u5411\u89e6\u53d1\u663e\u793a\u6d6e\u5c42\u7684\u5f53\u524d\u89e6\u53d1\u5143\u7d20(jQuery Node \u5bf9\u8c61)\u3002\n\n\n## \u4e8b\u4ef6\n\n### animated\n\n\u52a8\u753b\u6548\u679c\u7ed3\u675f\u65f6\u7684\u56de\u8c03\u4e8b\u4ef6\u3002`.on('animated', function(){ })`\n\n\n## \u6700\u4f73\u5b9e\u8df5\n\n```js\nseajs.use(['arale/popup/{{\u7248\u672c\u53f7}}/popup'], function(Popup){\n    var example = new Popup({\n        trigger: '#triggerId',\n        element: '#targetId'\n    });\n});\n```\n\n\u9700\u8981 tooltip \u6548\u679c\u7684\u8bf7\u5982\u4e0b\u8c03\u7528\uff1a\n\n```js\nseajs.use(['arale/popup/{{\u7248\u672c\u53f7}}/popup'], function(Popup){\n    var example = new Popup({\n        trigger: '#triggerId',\n        element: '#targetId',\n        delay: -1\n    });\n});\n```\n\n\u53e6\u5916\uff0cPopup \u5df2\u4ece Overlay \u7ee7\u627f\u4e86\u70b9\u51fb\u9875\u9762\u7a7a\u767d\u5904\u6d6e\u5c42\u6d88\u5931\uff0c\u4ee5\u53ca\u7a97\u53e3\u6539\u53d8\u5927\u5c0f\u540e\u6d6e\u5c42\u91cd\u65b0\u5b9a\u4f4d\u7b49\u88ab\u52a8\u5c5e\u6027\uff0c\n\u8be6\u7ec6\u8bf7\u67e5\u770b [\u6f14\u793a\u6587\u6863](http://aralejs.org/popup/examples/)\u3002\n\n\n### \u591a\u89e6\u53d1\u5668\u7684\u59d4\u6258\u5e94\u7528\n\n\u5b9e\u8df5\u4e2d\u5e38\u5e38\u9047\u5230\u591a\u4e2a\u89e6\u53d1\u5143\u7d20\u5bf9\u5e94\u4e00\u4e2a\u5f39\u51fa\u5c42\uff0c\u800c\u4e14\u89e6\u53d1\u5143\u7d20\u4f1a\u52a8\u6001\u6dfb\u52a0\u7684\u60c5\u51b5\u3002\n\u8fd9\u6837\u5982\u679c\u901a\u8fc7\u591a\u4e2a\u5b9e\u4f8b\u6765\u7ed1\u5b9a popup \u6548\u679c\u5c31\u4f1a\u6bd4\u8f83\u9ebb\u70e6\u3002\n\n\u8fd9\u65f6\uff0c\u53ef\u4ee5\u4f7f\u7528 `delegateNode` \u8fd9\u4e2a\u53c2\u6570\u5c06\u4e8b\u4ef6\u7ed1\u5b9a\u5230\u59d4\u6258\u8282\u70b9\u4e0a\uff0c\u914d\u5408\u591a\u4e2a trigger \u6765\u5b9e\u73b0\u3002\n\u5728\u59d4\u6258\u8282\u70b9\u5185\u52a8\u6001\u6dfb\u52a0\u4e86 trigger \u540e\uff0c\u4e5f\u65e0\u987b\u91cd\u65b0\u7ed1\u5b9a\u3002\n\n```js\nseajs.use(['popup'], function(Popup){\n    new Popup({\n        trigger: '.triggerClass',\n        element: '#popup',\n        delegateNode: '#delegateNode'\n    });\n});\n```\n[delegeteNode\u793a\u4f8b](examples/triggers.html#\u8303\u4f8b2-\u59d4\u6258\u4e8b\u4ef6)\n\n### \u52a8\u6001\u5185\u5bb9\n\n\u5f53\u6709\u591a\u4e2a\u89e6\u53d1\u5143\u7d20\uff0c\u800c\u5f39\u51fa\u5c42\u662f\u540c\u4e00\u4e2a\uff0c\u800c\u4e14\u5185\u5bb9\u662f\u6839\u636e\u4e0d\u540c\u89e6\u53d1\u5143\u7d20\u800c\u4e0d\u540c\u65f6\uff0c\u53ef\u4ee5\u7528\u4e0b\u9762\u7684\u65b9\u5f0f\u8fdb\u884c\u7ed1\u5b9a\uff1a\n\n```js\nseajs.use(['popup'], function(Popup){\n    new Popup({\n        trigger: '.triggerClass', // \u6709\u591a\u4e2a\u89e6\u53d1\u5143\u7d20\n        element: '#popup'\n    }).before('show', funtion() {\n      // \u901a\u8fc7 activeTrigger \u62ff\u5230\u5f53\u524d\u89e6\u53d1\u7684\u89e6\u53d1\u5143\u7d20\n      var content = this.activeTrigger.html();\n      // \u52a8\u6001\u8bbe\u5b9a\u5185\u5bb9\n      this.element.html(content);\n    });\n});\n```\n", "dependents": ["lcat/rec@0.0.1", "arale/tip@1.2.2", "customer/hqbao@0.1.0", "alinw/puzzle@1.0.0"], "tag": "stable", "homepage": "http://aralejs.org/popup/", "md5": "f5b760c4783b9c615f461892765e37c8", "description": "Popup \u662f\u53ef\u89e6\u53d1\u7684\u6d6e\u5c42\u7ec4\u4ef6\u3002"}